silf/__init__.py
silf/cli.py
silf/ect.py
silf/main.py
silf/scrab_img_from_lightshot.py
scrab_img_from_ligthshot-2.3.0.dist-info/LICENSE
scrab_img_from_ligthshot-2.3.0.dist-info/METADATA
scrab_img_from_ligthshot-2.3.0.dist-info/WHEEL
scrab_img_from_ligthshot-2.3.0.dist-info/entry_points.txt
scrab_img_from_ligthshot-2.3.0.dist-info/RECORD
