Metadata-Version: 2.1
Name: scrab-img-from-ligthshot
Version: 2.3.0
Summary: scrab images from ligthshot (i don't know is this legal)
Home-page: https://github.com/Transparency010101/scrab-img-from-ligthshot
License: Apache-2.0
Author: ossys
Author-email: ossys1010110@gmail.com
Requires-Python: >=3.11,<4.0
Classifier: License :: OSI Approved :: Apache Software License
Classifier: Programming Language :: Python :: 3
Classifier: Programming Language :: Python :: 3.11
Requires-Dist: argparse (>=1.4.0,<2.0.0)
Requires-Dist: beautifulsoup4 (>=4.12.2,<5.0.0)
Requires-Dist: fake-useragent (>=1.1.3,<2.0.0)
Requires-Dist: lxml (>=4.9.2,<5.0.0)
Requires-Dist: requests (>=2.30.0,<3.0.0)
Project-URL: Repository, https://github.com/Transparency010101/scrab-img-from-ligthshot
